sapiens_infinite_context_window/__init__.py
sapiens_infinite_context_window/sapiens_infinite_context_window.py
sapiens_infinite_context_window-1.0.5.dist-info/LICENSE.txt
sapiens_infinite_context_window-1.0.5.dist-info/METADATA
sapiens_infinite_context_window-1.0.5.dist-info/WHEEL
sapiens_infinite_context_window-1.0.5.dist-info/top_level.txt
sapiens_infinite_context_window-1.0.5.dist-info/RECORD
