Metadata-Version: 2.2
Name: sapiens_infinite_context_window
Version: 1.0.5
Home-page: https://github.com/sapiens-technology/SapiensInfiniteContextWindow
Author: SAPIENS TECHNOLOGY
License: Proprietary Software
License-File: LICENSE.txt
Requires-Dist: sapiens-embedding
Requires-Dist: scn
Dynamic: author
Dynamic: home-page
Dynamic: license
Dynamic: requires-dist
